mypythonlib/__init__.py
mypythonlib/auto_feature_eng.py
mypythonlib/myfunctions.py
auto_feat_eng-0.1.4.dist-info/METADATA
auto_feat_eng-0.1.4.dist-info/WHEEL
auto_feat_eng-0.1.4.dist-info/top_level.txt
auto_feat_eng-0.1.4.dist-info/RECORD
